{
    "availability": {
        "tier": 3
    },
    "crafting_items": {
        "normal": {
            "tag": "forge:gems/jasper"
        },
        "small": {
            "size": 9,
            "tag": "forge:nuggets/jasper"
        }
    },
    "name": {
        "name": "part.silentgems.main.jasper",
        "translate": true
    },
    "stats": [
        {
            "name": "durability",
            "value": 512
        },
        {
            "name": "armor_durability",
            "value": 14
        },
        {
            "name": "enchantability",
            "value": 16
        },
        {
            "name": "harvest_level",
            "value": 2
        },
        {
            "name": "harvest_speed",
            "value": 7
        },
        {
            "name": "melee_damage",
            "value": 3
        },
        {
            "name": "magic_damage",
            "value": 3
        },
        {
            "name": "attack_speed",
            "value": 0
        },
        {
            "name": "armor",
            "value": 18
        },
        {
            "name": "armor_toughness",
            "value": 4
        },
        {
            "name": "magic_armor",
            "value": 8
        },
        {
            "name": "ranged_damage",
            "value": 1
        },
        {
            "name": "ranged_speed",
            "value": -0.1
        },
        {
            "name": "chargeability",
            "value": 1.2
        },
        {
            "name": "rarity",
            "value": 30
        }
    ],
    "textures": {
        "all": {
            "lite_texture": "high_contrast",
            "highlight": true,
            "broken_color": "#A38800",
            "normal_color": "#FFFFFF",
            "texture_domain": "silentgems",
            "texture_suffix": "jasper"
        }
    },
    "traits": [
        {
            "level": 1,
            "name": "silentgear:brittle"
        }
    ],
    "type": "silentgear:main"
}