{
  "main/all": [
    {
      "texture": "silentgear:main_generic_hc",
      "color": "#FF8F7C6B"
    },
    {
      "texture": "silentgear:_highlight"
    }
  ],
  "main/fragment": [
    {
      "texture": "silentgear:metal",
      "color": "#FF8F7C6B"
    }
  ],
  "adornment/all": [
    {
      "texture": "silentgear:adornment_generic",
      "color": "#FF8F7C6B"
    }
  ],
  "adornment/part": [
    {
      "texture": "silentgear:adornment",
      "color": "#FF8F7C6B"
    },
    {
      "texture": "silentgear:adornment_highlight"
    }
  ]
}