{
    "display": {
        "icon": {
            "item": "silentgems:essenceore",
            "data": 0
        },
        "title": {
            "translate": "advancements.silentgems:get_chaosore.title"
        },
        "description": {
            "translate": "advancements.silentgems:get_chaosore.description"
        }
    },
    "parent": "silentgems:get_diamond_tips",
    "criteria": {
        "get_item": {
            "trigger": "minecraft:inventory_changed",
            "conditions": {
                "items": [
                    {
                        "item": "silentgems:essenceore",
                        "data": 0
                    }
                ]
            }
        }
    }
}