{
    "availability": {
        "tier": 3
    },
    "crafting_items": {
        "normal": {
            "tag": "forge:gems/ruby"
        },
        "small": {
            "size": 9,
            "tag": "forge:nuggets/ruby"
        }
    },
    "name": {
        "name": "part.silentgems.main.ruby",
        "translate": true
    },
    "stats": {
        "durability": 1024,
        "armor_durability": 24,
        "enchantability": 10,
        "harvest_level": 2,
        "harvest_speed": 8,
        "melee_damage": 5,
        "magic_damage": 2,
        "attack_speed": -0.3,
        "armor": 14,
        "armor_toughness": 2,
        "magic_armor": 4,
        "ranged_damage": 1,
        "ranged_speed": -0.2,
        "rarity": 25,
        "silentgems:chargeability": 1.1
    },
    "textures": {
        "all": {
            "lite_texture": "high_contrast",
            "highlight": true,
            "armor_color": "#FFFFFF",
            "broken_color": "#E61D1D",
            "normal_color": "#FFFFFF",
            "texture_domain": "silentgems",
            "texture_suffix": "ruby"
        }
    },
    "traits": [
        {
            "name": "silentgems:imperial",
            "level": 3
        },
        {
            "name": "silentgear:brittle",
            "level": 1
        }
    ],
    "type": "silentgear:main"
}