{
  "type": "silentgems:token_enchanting",
  "chaosGenerated": 500,
  "processTime": 200,
  "ingredients": {
    "token": {
      "item": "silentgems:blank_token"
    },
    "others": [
      {
        "tag": "forge:gems/moonstone",
        "count": 2
      },
      {
        "item": "silentgems:ender_frost",
        "count": 4
      },
      {
        "item": "minecraft:blue_ice",
        "count": 2
      }
    ]
  },
  "result": {
    "item": "silentgems:enchantment_token",
    "enchantments": [
      {
        "name": "minecraft:frost_walker",
        "level": 1
      }
    ]
  }
}